more/browser_session/__init__.py
more/browser_session/app.py
more/browser_session/sessions.py
more_browser_session-23.2.0.dist-info/LICENSE
more_browser_session-23.2.0.dist-info/METADATA
more_browser_session-23.2.0.dist-info/WHEEL
more_browser_session-23.2.0.dist-info/RECORD
