Metadata-Version: 2.1
Name: more-browser-session
Version: 23.2.0
Summary: Session support for Morepath applications
Home-page: https://github.com/edemocracy/more.browser_session
License: BSD-3-Clause
Keywords: morepath,session,web,http
Author: Tobias dpausp
Author-email: dpausp@posteo.de
Requires-Python: >=3.10,<4.0
Classifier: License :: OSI Approved :: BSD License
Classifier: Programming Language :: Python :: 3
Classifier: Programming Language :: Python :: 3.10
Classifier: Programming Language :: Python :: 3.11
Requires-Dist: Werkzeug (>=2.2.2,<3.0.0)
Requires-Dist: itsdangerous (>=2.1.2,<3.0.0)
Requires-Dist: morepath (>=0.19,<0.20)
Project-URL: Repository, https://github.com/edemocracy/more.browser_session
